commons_codec/__init__.py
commons_codec/exception.py
commons_codec/model.py
commons_codec/decode/__init__.py
commons_codec/decode/sensor_community.py
commons_codec/decode/tasmota.py
commons_codec/decode/tts_ttn.py
commons_codec/transform/__init__.py
commons_codec/transform/aws_dms.py
commons_codec/transform/dynamodb.py
commons_codec/transform/dynamodb_model.py
commons_codec/transform/mongodb.py
commons_codec/util/__init__.py
commons_codec/util/data.py
commons_codec/util/io.py
commons_codec/vendor/__init__.py
commons_codec/vendor/boto3/__init__.py
commons_codec/vendor/boto3/dynamodb/__init__.py
commons_codec/vendor/boto3/dynamodb/types.py
commons_codec-0.0.24.dist-info/licenses/LICENSE
commons_codec-0.0.24.dist-info/METADATA
commons_codec-0.0.24.dist-info/WHEEL
commons_codec-0.0.24.dist-info/top_level.txt
commons_codec-0.0.24.dist-info/RECORD
