Metadata-Version: 2.4
Name: commons-codec
Version: 0.0.24
Summary: Data decoding, encoding, conversion, and translation utilities.
Author-email: Andreas Motl <andreas.motl@panodata.org>
License: LGPL 3, EUPL 1.2
Project-URL: Changelog, https://commons-codec.readthedocs.io/changes.html
Project-URL: Documentation, https://commons-codec.readthedocs.io/
Project-URL: Homepage, https://commons-codec.readthedocs.io/
Project-URL: Issues, https://github.com/daq-tools/commons-codec/issues
Project-URL: Repository, https://github.com/daq-tools/commons-codec
Keywords: airrohr,bson,cdc,conversion,convert,data,decode,deserialize,dynamodb,encode,i/o,jmespath,json,jsonpointer,luftdaten.info,map data,marshal,mongodb,nested data,sensor.community,serialize,sql,tasmota,tikray,tool,transcode,transform,translate,transon,ttn,tts,unmarshal,unserialize,utility
Classifier: Development Status :: 4 - Beta
Classifier: Environment :: Plugins
Classifier: Intended Audience :: Developers
Classifier: Intended Audience :: Education
Classifier: Intended Audience :: Information Technology
Classifier: Intended Audience :: Manufacturing
Classifier: Intended Audience :: Science/Research
Classifier: Intended Audience :: System Administrators
Classifier: Intended Audience :: Telecommunications Industry
Classifier: License :: OSI Approved :: European Union Public Licence 1.2 (EUPL 1.2)
Classifier: License :: OSI Approved :: GNU Lesser General Public License v3 (LGPLv3)
Classifier: Operating System :: OS Independent
Classifier: Operating System :: POSIX :: Linux
Classifier: Operating System :: Unix
Classifier: Programming Language :: Python
Classifier: Programming Language :: Python :: 3 :: Only
Classifier: Programming Language :: Python :: 3.8
Classifier: Programming Language :: Python :: 3.9
Classifier: Programming Language :: Python :: 3.10
Classifier: Programming Language :: Python :: 3.11
Classifier: Programming Language :: Python :: 3.12
Classifier: Programming Language :: Python :: 3.13
Classifier: Programming Language :: Python :: Implementation :: CPython
Classifier: Programming Language :: Python :: Implementation :: PyPy
Classifier: Programming Language :: SQL
Classifier: Topic :: Adaptive Technologies
Classifier: Topic :: Communications
Classifier: Topic :: Database
Classifier: Topic :: Documentation
Classifier: Topic :: Education
Classifier: Topic :: Internet
Classifier: Topic :: Office/Business
Classifier: Topic :: Scientific/Engineering
Classifier: Topic :: Scientific/Engineering :: Information Analysis
Classifier: Topic :: Scientific/Engineering :: Interface Engine/Protocol Translator
Classifier: Topic :: Software Development :: Libraries
Classifier: Topic :: Software Development :: Pre-processors
Classifier: Topic :: Software Development :: Testing
Classifier: Topic :: Software Development :: Version Control
Classifier: Topic :: System :: Archiving
Classifier: Topic :: System :: Benchmark
Classifier: Topic :: System :: Clustering
Classifier: Topic :: System :: Distributed Computing
Classifier: Topic :: System :: Logging
Classifier: Topic :: System :: Monitoring
Classifier: Topic :: System :: Networking
Classifier: Topic :: System :: Systems Administration
Classifier: Topic :: Text Processing
Classifier: Topic :: Utilities
Requires-Python: >=3.8.6
License-File: LICENSE
Requires-Dist: attrs<26
Requires-Dist: backports-strenum<1.3; python_version < "3.11"
Requires-Dist: cattrs<26
Requires-Dist: importlib-resources<6.5; python_version < "3.10"
Requires-Dist: python-dateutil<3
Requires-Dist: simplejson<4
Requires-Dist: sqlalchemy-cratedb>=0.39.0
Requires-Dist: toolz<1.1
Provides-Extra: all
Requires-Dist: commons-codec[mongodb,tikray]; extra == "all"
Provides-Extra: develop
Requires-Dist: mypy<1.17; extra == "develop"
Requires-Dist: poethepoet<1; extra == "develop"
Requires-Dist: pyproject-fmt<3; extra == "develop"
Requires-Dist: ruff<0.13; extra == "develop"
Requires-Dist: validate-pyproject<1; extra == "develop"
Provides-Extra: doc
Requires-Dist: furo==2024.1.29; extra == "doc"
Requires-Dist: myst-parser[linkify]<5,>=0.18; extra == "doc"
Requires-Dist: sphinx-autobuild==2021.3.14; extra == "doc"
Requires-Dist: sphinx-copybutton; extra == "doc"
Requires-Dist: sphinx-design-elements<1; extra == "doc"
Requires-Dist: sphinxcontrib-mermaid<2; extra == "doc"
Requires-Dist: sphinxext-opengraph<1; extra == "doc"
Provides-Extra: mongodb
Requires-Dist: pymongo<4.14; extra == "mongodb"
Provides-Extra: release
Requires-Dist: build<2; extra == "release"
Requires-Dist: twine<7; extra == "release"
Provides-Extra: test
Requires-Dist: cratedb-toolkit[testing]; extra == "test"
Requires-Dist: pytest<9; extra == "test"
Requires-Dist: pytest-cov<7; extra == "test"
Requires-Dist: pytest-mock<4; extra == "test"
Provides-Extra: tikray
Requires-Dist: tikray<0.3,>=0.2.2; extra == "tikray"
Dynamic: license-file
